pub_package/__init__.py
pub_package/pdf2image.py
pub_package/pdf2text.py
chamathpdf-0.0.1.dist-info/LICENCE
chamathpdf-0.0.1.dist-info/METADATA
chamathpdf-0.0.1.dist-info/WHEEL
chamathpdf-0.0.1.dist-info/top_level.txt
chamathpdf-0.0.1.dist-info/RECORD
